[{"doorIndex":0,"subIndex":0,"bossId":171,"enemyLv":50,"enemyDv":31,"enemyNature":-1,"enemyHpOverride":0,"rewardItemId":400110,"rewardPetId":0},{"doorIndex":1,"subIndex":0,"bossId":174,"enemyLv":60,"enemyDv":31,"enemyNature":-1,"enemyHpOverride":0,"rewardItemId":400111,"rewardPetId":0},{"doorIndex":2,"subIndex":0,"bossId":177,"enemyLv":70,"enemyDv":31,"enemyNature":-1,"enemyHpOverride":0,"rewardItemId":400112,"rewardPetId":0},{"doorIndex":2,"subIndex":1,"bossId":183,"enemyLv":75,"enemyDv":31,"enemyNature":-1,"enemyHpOverride":0,"rewardItemId":400113,"rewardPetId":0},{"doorIndex":3,"subIndex":0,"bossId":195,"enemyLv":80,"enemyDv":31,"enemyNature":-1,"enemyHpOverride":0,"rewardItemId":400115,"rewardPetId":0},{"doorIndex":3,"subIndex":1,"bossId":192,"enemyLv":85,"enemyDv":31,"enemyNature":-1,"enemyHpOverride":0,"rewardItemId":400116,"rewardPetId":0},{"doorIndex":4,"subIndex":0,"bossId":222,"enemyLv":90,"enemyDv":31,"enemyNature":-1,"enemyHpOverride":0,"rewardItemId":400120,"rewardPetId":0},{"doorIndex":4,"subIndex":1,"bossId":224,"enemyLv":95,"enemyDv":31,"enemyNature":-1,"enemyHpOverride":0,"rewardItemId":400121,"rewardPetId":0},{"doorIndex":4,"subIndex":2,"bossId":227,"enemyLv":100,"enemyDv":31,"enemyNature":-1,"enemyHpOverride":0,"rewardItemId":400122,"rewardPetId":0},{"doorIndex":5,"subIndex":0,"bossId":359,"enemyLv":100,"enemyDv":31,"enemyNature":-1,"enemyHpOverride":0,"rewardItemId":400130,"rewardPetId":0},{"doorIndex":5,"subIndex":1,"bossId":297,"enemyLv":100,"enemyDv":31,"enemyNature":-1,"enemyHpOverride":0,"rewardItemId":400128,"rewardPetId":0},{"doorIndex":5,"subIndex":2,"bossId":356,"enemyLv":100,"enemyDv":31,"enemyNature":-1,"enemyHpOverride":0,"rewardItemId":400129,"rewardPetId":0},{"doorIndex":6,"subIndex":0,"bossId":438,"enemyLv":100,"enemyDv":31,"enemyNature":-1,"enemyHpOverride":0,"rewardItemId":400142,"rewardPetId":0},{"doorIndex":6,"subIndex":1,"bossId":441,"enemyLv":100,"enemyDv":31,"enemyNature":-1,"enemyHpOverride":0,"rewardItemId":400143,"rewardPetId":0},{"doorIndex":6,"subIndex":2,"bossId":435,"enemyLv":100,"enemyDv":31,"enemyNature":-1,"enemyHpOverride":0,"rewardItemId":400144,"rewardPetId":0},{"doorIndex":7,"subIndex":0,"bossId":656,"enemyLv":100,"enemyDv":31,"enemyNature":-1,"enemyHpOverride":0,"rewardItemId":400184,"rewardPetId":0},{"doorIndex":7,"subIndex":1,"bossId":659,"enemyLv":100,"enemyDv":31,"enemyNature":-1,"enemyHpOverride":0,"rewardItemId":400185,"rewardPetId":0},{"doorIndex":7,"subIndex":2,"bossId":661,"enemyLv":100,"enemyDv":31,"enemyNature":-1,"enemyHpOverride":0,"rewardItemId":400186,"rewardPetId":0},{"doorIndex":8,"subIndex":0,"bossId":779,"enemyLv":100,"enemyDv":31,"enemyNature":-1,"enemyHpOverride":0,"rewardItemId":400197,"rewardPetId":0},{"doorIndex":8,"subIndex":1,"bossId":784,"enemyLv":100,"enemyDv":31,"enemyNature":-1,"enemyHpOverride":0,"rewardItemId":400199,"rewardPetId":0},{"doorIndex":8,"subIndex":2,"bossId":782,"enemyLv":100,"enemyDv":31,"enemyNature":-1,"enemyHpOverride":0,"rewardItemId":400198,"rewardPetId":0},{"doorIndex":9,"subIndex":0,"bossId":1182,"enemyLv":100,"enemyDv":31,"enemyNature":-1,"enemyHpOverride":0,"rewardItemId":400304,"rewardPetId":0},{"doorIndex":9,"subIndex":1,"bossId":1185,"enemyLv":100,"enemyDv":31,"enemyNature":-1,"enemyHpOverride":0,"rewardItemId":400305,"rewardPetId":0},{"doorIndex":9,"subIndex":2,"bossId":1187,"enemyLv":100,"enemyDv":31,"enemyNature":-1,"enemyHpOverride":0,"rewardItemId":400306,"rewardPetId":0},{"doorIndex":10,"subIndex":0,"bossId":1403,"enemyLv":100,"enemyDv":31,"enemyNature":-1,"enemyHpOverride":0,"rewardItemId":400429,"rewardPetId":0},{"doorIndex":10,"subIndex":1,"bossId":1397,"enemyLv":100,"enemyDv":31,"enemyNature":-1,"enemyHpOverride":0,"rewardItemId":400430,"rewardPetId":0},{"doorIndex":10,"subIndex":2,"bossId":1400,"enemyLv":100,"enemyDv":31,"enemyNature":-1,"enemyHpOverride":0,"rewardItemId":400431,"rewardPetId":0},{"doorIndex":11,"subIndex":0,"bossId":169,"enemyLv":50,"enemyDv":31,"enemyNature":-1,"enemyHpOverride":0,"rewardItemId":400109,"rewardPetId":0,"remark":"试炼之门"}]
